dendrox/__init__.py
dendrox-0.1.1.dist-info/METADATA
dendrox-0.1.1.dist-info/WHEEL
dendrox-0.1.1.dist-info/licenses/LICENSE
dendrox-0.1.1.dist-info/RECORD
